Metadata-Version: 2.4
Name: truffle-sdk
Version: 0.9.3
Summary: The SDK for TruffleOS cloud/hardware agents
Author: Deepshard
Author-email: accounts@deepshard.org
License: MIT
Requires-Python: >=3.10
Requires-Dist: grpcio==1.69.0
Requires-Dist: grpcio-reflection==1.69.0
Requires-Dist: protobuf==5.29.3
Requires-Dist: requests==2.32.3
Dynamic: author
Dynamic: author-email
Dynamic: license
Dynamic: requires-dist
Dynamic: requires-python
Dynamic: summary
